scrapebadger_mcp/__init__.py
scrapebadger_mcp/py.typed
scrapebadger_mcp/server.py
scrapebadger_mcp-0.1.1.dist-info/METADATA
scrapebadger_mcp-0.1.1.dist-info/WHEEL
scrapebadger_mcp-0.1.1.dist-info/entry_points.txt
scrapebadger_mcp-0.1.1.dist-info/licenses/LICENSE
scrapebadger_mcp-0.1.1.dist-info/RECORD
