Metadata-Version: 2.4
Name: scrapebadger-mcp
Version: 0.1.1
Summary: MCP server for ScrapeBadger - Twitter/X scraping API for AI agents
Project-URL: Homepage, https://scrapebadger.com
Project-URL: Documentation, https://docs.scrapebadger.com
Project-URL: Repository, https://github.com/scrape-badger/scrapebadger-mcp
Project-URL: Issues, https://github.com/scrape-badger/scrapebadger-mcp/issues
Author-email: ScrapeBadger <support@scrapebadger.com>
License: MIT
License-File: LICENSE
Keywords: ai,api,chatgpt,claude,cursor,llm,mcp,model-context-protocol,scraping,twitter,x
Classifier: Development Status :: 4 - Beta
Classifier: Intended Audience :: Developers
Classifier: License :: OSI Approved :: MIT License
Classifier: Operating System :: OS Independent
Classifier: Programming Language :: Python :: 3
Classifier: Programming Language :: Python :: 3.10
Classifier: Programming Language :: Python :: 3.11
Classifier: Programming Language :: Python :: 3.12
Classifier: Programming Language :: Python :: 3.13
Classifier: Topic :: Internet :: WWW/HTTP :: Indexing/Search
Classifier: Topic :: Software Development :: Libraries :: Python Modules
Classifier: Typing :: Typed
Requires-Python: >=3.10
Requires-Dist: mcp>=1.0.0
Requires-Dist: pydantic>=2.0.0
Requires-Dist: scrapebadger>=0.1.0
Provides-Extra: dev
Requires-Dist: mypy>=1.13.0; extra == 'dev'
Requires-Dist: pytest-asyncio>=0.23.0; extra == 'dev'
Requires-Dist: pytest>=8.0.0; extra == 'dev'
Requires-Dist: ruff>=0.8.0; extra == 'dev'
